gazefollower/GazeFollower.py
gazefollower/__init__.py
gazefollower/version.py
gazefollower/calibration/Calibration.py
gazefollower/calibration/CalibrationController.py
gazefollower/calibration/SVRCalibration.py
gazefollower/calibration/__init__.py
gazefollower/camera/Camera.py
gazefollower/camera/WebCamCamera.py
gazefollower/camera/__init__.py
gazefollower/face_alignment/BlazeFaceAlignment.py
gazefollower/face_alignment/FaceAlignment.py
gazefollower/face_alignment/MediaPipeFaceAlignment.py
gazefollower/face_alignment/__init__.py
gazefollower/filter/Filter.py
gazefollower/filter/HeuristicFilter.py
gazefollower/filter/OneEuroFilter.py
gazefollower/filter/__init__.py
gazefollower/finetuning/__init__.py
gazefollower/gaze_estimator/GazeEstimator.py
gazefollower/gaze_estimator/MGazeNetGazeEstimator.py
gazefollower/gaze_estimator/__init__.py
gazefollower/logger/Logger.py
gazefollower/logger/__init__.py
gazefollower/misc/DefaultConfig.py
gazefollower/misc/Enumeration.py
gazefollower/misc/FaceInfo.py
gazefollower/misc/GazeInfo.py
gazefollower/misc/Recorder.py
gazefollower/misc/TriggerHandler.py
gazefollower/misc/__init__.py
gazefollower/res/audio/beep.wav
gazefollower/res/image/dot.png
gazefollower/res/image/face.jpg
gazefollower/res/image/frame.jpg
gazefollower/res/image/gazefollower.png
gazefollower/res/image/left_arrow.png
gazefollower/res/image/left_eye.jpg
gazefollower/res/image/right_eye.jpg
gazefollower/res/model_weights/base.mnn
gazefollower/ui/BaseUI.py
gazefollower/ui/CalibrationUI.py
gazefollower/ui/CameraPreviewerUI.py
gazefollower/ui/ParticipantInfoDialog.py
gazefollower/ui/UIBackend.py
gazefollower/ui/__init__.py
gazefollower-1.0.2.dist-info/LICENSE-CC-BY-NC-SA
gazefollower-1.0.2.dist-info/METADATA
gazefollower-1.0.2.dist-info/WHEEL
gazefollower-1.0.2.dist-info/top_level.txt
gazefollower-1.0.2.dist-info/RECORD
