Metadata-Version: 2.1
Name: gazefollower
Version: 1.0.2
Summary: GazeFollower is a pythonic library for web-cam gaze tracking. 
Home-page: https://github.com/GanchengZhu/GazeFollower
Author: Gancheng Zhu
Author-email: zhugc2016@gmail.com
Classifier: Programming Language :: Python :: 3
Classifier: Operating System :: OS Independent
Classifier: Development Status :: 5 - Production/Stable
Classifier: Intended Audience :: Developers
Requires-Python: >=3.7
License-File: LICENSE-CC-BY-NC-SA
Requires-Dist: mediapipe
Requires-Dist: MNN
Requires-Dist: numpy
Requires-Dist: opencv-python
Requires-Dist: pandas
Requires-Dist: pygame
Requires-Dist: screeninfo
